multi_tokenizer/__init__.py
multi_tokenizer/language_detect.py
multi_tokenizer/pretrained/__init__.py
multi_tokenizer/pretrained/chinese_tokenizer.json
multi_tokenizer/pretrained/english_tokenizer.json
multi_tokenizer/pretrained/hindi_tokenizer.json
multi_tokenizer/pretrained/spanish_tokenizer.json
multi_tokenizer/tokenizer.py
multi_tokenizer-0.1.4.dist-info/LICENSE
multi_tokenizer-0.1.4.dist-info/METADATA
multi_tokenizer-0.1.4.dist-info/WHEEL
multi_tokenizer-0.1.4.dist-info/RECORD
