Metadata-Version: 2.1
Name: multi-tokenizer
Version: 0.1.4
Summary: Python package that provides tokenization of multilingual texts using language-specific tokenizers
License: MIT
Author: chandralegend
Author-email: irugalbandarachandra@gmail.com
Requires-Python: >=3.8.19,<4.0.0
Classifier: License :: OSI Approved :: MIT License
Classifier: Programming Language :: Python :: 3
Classifier: Programming Language :: Python :: 3.9
Classifier: Programming Language :: Python :: 3.10
Classifier: Programming Language :: Python :: 3.11
Classifier: Programming Language :: Python :: 3.12
Requires-Dist: lingua-language-detector (>=2.0.2,<3.0.0)
Requires-Dist: tokenizers (>=0.19.1,<0.20.0)
